{
  "users": [
    {
      "id": "admin@ad.ad",
      "password": "f6fdffe48c908deb0f4c3bd36c032e72",
      "name": "dsffdsf"
    },
    {
      "id": "admin@ad.ad2",
      "password": "f6fdffe48c908deb0f4c3bd36c032e72",
      "name": "22"
    },
    {
      "id": "admin@ad.ad3",
      "password": "f6fdffe48c908deb0f4c3bd36c032e72",
      "name": "33"
    }
  ],
  "questions": [
    {
      "author": "admin@ad.ad",
      "isDecided": false,
      "isDeleted": false,
      "tags": [],
      "title": "111",
      "body": "111",
      "ratingPlus": [],
      "ratingMinus": [],
      "createdDateUnix": "1514680992706",
      "id": 0
    },
    {
      "author": "admin@ad.ad",
      "isDecided": false,
      "isDeleted": false,
      "tags": [
        2,
        3,
        4
      ],
      "title": "a",
      "body": "aaa",
      "ratingPlus": [],
      "ratingMinus": [],
      "createdDateUnix": "1514721793156",
      "id": 1
    },
    {
      "author": "admin@ad.ad",
      "isDecided": false,
      "isDeleted": false,
      "tags": [
        5,
        6,
        2
      ],
      "title": "z",
      "body": "zzz",
      "ratingPlus": [],
      "ratingMinus": [],
      "createdDateUnix": "1514721813881",
      "id": 2
    }
  ],
  "tags": [
    {
      "id": 0,
      "title": "jquery"
    },
    {
      "id": 1,
      "title": "js"
    },
    {
      "title": "a",
      "id": 2
    },
    {
      "title": "s",
      "id": 3
    },
    {
      "title": "d",
      "id": 4
    },
    {
      "title": "z",
      "id": 5
    },
    {
      "title": "x",
      "id": 6
    }
  ]
}